streamlit_bls_connection/__init__.py
streamlit_bls_connection/bls_connection.py
streamlit_bls_connection/version.py
streamlit_bls_connection-0.9.dist-info/LICENSE
streamlit_bls_connection-0.9.dist-info/METADATA
streamlit_bls_connection-0.9.dist-info/WHEEL
streamlit_bls_connection-0.9.dist-info/top_level.txt
streamlit_bls_connection-0.9.dist-info/RECORD
